raya/__init__.py
raya/application_base.py
raya/constans.py
raya/constants.py
raya/entry_point.py
raya/enumerations.py
raya/example.py
raya/exceptions.py
raya/logger.py
raya/raya_interface.py
raya/controllers/__init__.py
raya/controllers/arms_controller.py
raya/controllers/base_controller.py
raya/controllers/base_pseudo_controller.py
raya/controllers/cameras_controller.py
raya/controllers/communication_controller.py
raya/controllers/cv_controller.py
raya/controllers/grasping_controller.py
raya/controllers/interactions_controller.py
raya/controllers/leds_controller.py
raya/controllers/lidar_controller.py
raya/controllers/motion_controller.py
raya/controllers/navigation_controller.py
raya/controllers/sensors_controller.py
raya/controllers/skills_controller.py
raya/controllers/sound_controller.py
raya/controllers/ui_controller.py
raya/listeners/__init__.py
raya/listeners/cameras_listeners.py
raya/listeners/lidar_listeners.py
raya/listeners/sensors_listeners.py
raya/tools/__init__.py
raya/tools/image.py
raya/utils/__init__.py
raya/utils/app_utils.py
raya/utils/numeric.py
raya/utils/py_utils.py
raya_os-0.1.2.dist-info/LICENSE
raya_os-0.1.2.dist-info/METADATA
raya_os-0.1.2.dist-info/WHEEL
raya_os-0.1.2.dist-info/top_level.txt
raya_os-0.1.2.dist-info/RECORD
