Metadata-Version: 2.1
Name: raya-os
Version: 0.1.2
Summary: Raya OS skelaton
Home-page: UNKNOWN
Author: Ofir Ozeri
Author-email: ofiro@unlimited-robotics.com
License: MIT
Platform: UNKNOWN
Requires-Python: >=3.8
License-File: LICENSE
Requires-Dist: rayasdk
